setup.py
hoiio/__init__.py
hoiio/exceptions.py
hoiio/utils.py
hoiio.egg-info/PKG-INFO
hoiio.egg-info/SOURCES.txt
hoiio.egg-info/dependency_links.txt
hoiio.egg-info/requires.txt
hoiio.egg-info/top_level.txt
hoiio/service/__init__.py
hoiio/service/account.py
hoiio/service/fax.py
hoiio/service/ivr.py
hoiio/service/number.py
hoiio/service/sms.py
hoiio/service/voice.py