Metadata-Version: 1.0
Name: hoiio
Version: 0.1.4
Summary: Python SDK for Hoiio API
Home-page: http://developer.hoiio.com
Author: Junda Ong
Author-email: junda@hoiio.com
License: MIT
Keywords: hoiio voice sms conference fax ivr
Platform: UNKNOWN
Classifier: Intended Audience :: Developers
Classifier: License :: OSI Approved :: MIT License
Classifier: Operating System :: OS Independent
Classifier: Programming Language :: Python
Classifier: Programming Language :: Python :: 2.5
Classifier: Programming Language :: Python :: 2.6
Classifier: Programming Language :: Python :: 2.7
Classifier: Topic :: Software Development :: Libraries :: Python Modules
Classifier: Topic :: Communications :: Telephony
